.gitignore
.travis.yml
MANIFEST.in
README.rst
base.cfg
bootstrap.py
buildout.cfg
setup.py
test-4.0.x.cfg
test-4.1.x.cfg
test-4.2.x.cfg
test-4.3.x.cfg
test-4.4.x.cfg
travis-4.0.x.cfg
travis-4.1.x.cfg
travis-4.2.x.cfg
travis-4.3.x.cfg
travis-4.4.x.cfg
version.txt
bin/rebuildjs.sh
docs/CHANGES.rst
docs/INSTALL.rst
docs/LICENSE.GPL
docs/LICENSE.txt
scripts/sync_from_generic.sh
seleniums/c.selenium
src.mrdeveloper/.empty
src/collective/__init__.py
src/collective.js.chosen.egg-info/PKG-INFO
src/collective.js.chosen.egg-info/SOURCES.txt
src/collective.js.chosen.egg-info/dependency_links.txt
src/collective.js.chosen.egg-info/entry_points.txt
src/collective.js.chosen.egg-info/namespace_packages.txt
src/collective.js.chosen.egg-info/requires.txt
src/collective.js.chosen.egg-info/top_level.txt
src/collective/js/__init__.py
src/collective/js/chosen/__init__.py
src/collective/js/chosen/app_config.py
src/collective/js/chosen/configure.zcml
src/collective/js/chosen/interfaces.py
src/collective/js/chosen/profiles.zcml
src/collective/js/chosen/rebuild_i18n.sh
src/collective/js/chosen/setuphandlers.py
src/collective/js/chosen/testing.py
src/collective/js/chosen/version.txt
src/collective/js/chosen/Extensions/__init__.py
src/collective/js/chosen/browser/__init__.py
src/collective/js/chosen/browser/configure.zcml
src/collective/js/chosen/browser/template.pt
src/collective/js/chosen/browser/view.py
src/collective/js/chosen/browser/viewlet.pt
src/collective/js/chosen/browser/viewlets.py
src/collective/js/chosen/browser/resources/README.txt
src/collective/js/chosen/browser/resources/ajax-chosen.js
src/collective/js/chosen/browser/resources/ajax-chosen.min.js
src/collective/js/chosen/browser/resources/chosen-sprite.png
src/collective/js/chosen/browser/resources/chosen.css
src/collective/js/chosen/browser/resources/chosen.jquery.js
src/collective/js/chosen/browser/resources/chosen.jquery.min.js
src/collective/js/chosen/browser/resources/chosen.proto.js
src/collective/js/chosen/browser/resources/chosen.proto.min.js
src/collective/js/chosen/locales/collective.js.chosen-manual.pot
src/collective/js/chosen/locales/collective.js.chosen.pot
src/collective/js/chosen/locales/fr/LC_MESSAGES/collective.js.chosen.po
src/collective/js/chosen/migrations/__init__.py
src/collective/js/chosen/migrations/configure.zcml
