Metadata-Version: 1.1
Name: collective.js.chosen
Version: 1.4
Summary: Integrate chosen and ajaxchosen in plone
Home-page: http://pypi.python.org/pypi/collective.js.chosen
Author: kiorky
Author-email: kiorky@cryptelium.net
License: GPL
Platform: UNKNOWN
Classifier: Framework :: Plone
Classifier: Framework :: Plone :: 4.0
Classifier: Framework :: Plone :: 4.1
Classifier: Framework :: Plone :: 4.2
Classifier: Programming Language :: Python
Classifier: Topic :: Software Development
